Workbook

Sheet Página de Instruções
A1: Bem vindo ao Relatório de Resultados DEV2B!
A3: O Objetivo desse documento é fornecer à você uma visão analítica do resultado da sua Clínica. Oferecento uma visão de Faturamento, Custos e Resultas que você vem tendo ao longo do Ano.
A5: Para que a planilha funciona de forma adequada, por favor seguir o passo a passo descrito abaixo:
A7: 1-) Depois de realizar o Login no Agendart, clique na página de Financeiro > À Receber > Filtrar. Nesse Filtro, alterar a data para 01/01/2025 até o dia de hoje e em seguida clique em "Aplicar" conforme Imagem abaixo
A26: 2-) O próximo passo é exportar o arquivo para Excel. Para isso desça a tela até aparecer o botão "Exportar" que vai estar localizado na parte debaixo da tabela. Clique no botão e escolha a opção "Exportar Excel"
A49: 3-) Agora você deve abrir o arquivo que foi exportado para seu computador. Com ele aberto, selecione as colunas de A:A até U:U e copie e cole neste aquivo na célula A1 na aba "Atendimentos à Receber"
A50: 4-) Agora vamos precisar Exportar o Arquivo de Mensalidades. Ele fica na na terceira aba da página de Financeiro. Também selecione no filtro, as datas do dia 01/01/2025 até hoje. E em seguida realize a exportação de dados para o excel no mesmo padrão da etapa anterior
A51: 5-) Agora vamos abrir esse novo arquivo que foi exportado para o seu computador. Com ele aberto, selecione as colunas A:A até H:H e cole na célula A1 na aba "Outras Contas à Receber"
A52: Primeira Parte concluída! Agora a planilha já esta registrando todos os faturamentos da Clínica! Agora A segunda parte é registrar os Custos que a Clínica teve.
A53: 6-) Clique na página de Financeiro > À Pagar > Filtrar. Nesse Filtro, alterar a data para 01/01/2024 até o dia de hoje e em seguida clique em "Aplicar" conforme Imagem abaixo
A71: 7-) Agora vamos precisar Exportar o Arquivo de Contas A Pagar. Ele fica na mesma página do Agendart que você está agora, só que bem no final dela. Desça toda a página e você vai encontar outro botão "Exportar Dados". Assim como anteriormente, selecione a opção "Exportar Excel"
A72: 8-) Agora vamos abrir esse novo arquivo que foi exportado para o seu computador. Com ele aberto, selecione as colunas A:A até G:G e cole na célula A1 na aba "Contas à Pagar"
A73: 9-) Agora, se quiser realizar uma análise de algum profissional específico da Clínica, é possível fazer na Aba "Resultado Profissional" Basta escrever o nome do profissional igual ao cadastrado no Agendart na Célula B3.

Sheet Resultado Clinica
B1: Resultados da Clinica
C3: Acumulado no Ano | D3: 45658 | E3: 45689 | F3: 45717 | G3: 45748 | H3: 45778 | I3: 45809 | J3: 45839 | K3: 45870 | L3: 45901 | M3: 45931 | N3: 45962 | O3: 45992
B4: Faturamento | C4: =SUM(D4:O4) -> 0 | D4: =SUM(D5:D6) -> 0 | E4: =SUM(E5:E6) -> 0 | F4: =SUM(F5:F6) -> 0 | G4: =SUM(G5:G6) -> 0 | H4: =SUM(H5:H6) -> 0 | I4: =SUM(I5:I6) -> 0 | J4: =SUM(J5:J6) -> 0 | K4: =SUM(K5:K6) -> 0 | ... O4: =SUM(O5:O6) -> 0
B5: Recebimento Pacientes | C5: =SUM(D5:O5) -> 0 | D5: =SUMIFS('Atendimentos à Receber'!$R:$R,'Atendimentos à Receber'!$V:$V,">="&45658,'Atendimentos à Receber'!$V:$V,"<="&45688) -> 0 | E5: =SUMIFS('Atendimentos à Receber'!$R:$R,'Atendimentos à Receber'!$V:$V,">="&45689,'Atendimentos à Receber'!$V:$V,"<="&45716) -> 0 | F5: =SUMIFS('Atendimentos à Receber'!$R:$R,'Atendimentos à Receber'!$V:$V,">="&45717,'Atendimentos à Receber'!$V:$V,"<="&45748) -> 0 | G5: =SUMIFS('Atendimentos à Receber'!$R:$R,'Atendimentos à Receber'!$V:$V,">="&45748,'Atendimentos à Receber'!$V:$V,"<="&45777) -> 0 | H5: =SUMIFS('Atendimentos à Receber'!$R:$R,'Atendimentos à Receber'!$V:$V,">="&45778,'Atendimentos à Receber'!$V:$V,"<="&45808) -> 0 | I5: =SUMIFS('Atendimentos à Receber'!$R:$R,'Atendimentos à Receber'!$V:$V,">="&45809,'Atendimentos à Receber'!$V:$V,"<="&45838) -> 0 | J5: =SUMIFS('Atendimentos à Receber'!$R:$R,'Atendimentos à Receber'!$V:$V,">="&45839,'Atendimentos à Receber'!$V:$V,"<="&45869) -> 0 | K5: =SUMIFS('Atendimentos à Receber'!$R:$R,'Atendimentos à Receber'!$V:$V,">="&45870,'Atendimentos à Receber'!$V:$V,"<="&45900) -> 0 | L5: =SUMIFS('Atendimentos à Receber'!$R:$R,'Atendimentos à Receber'!$V:$V,">="&45901,'Atendimentos à Receber'!$V:$V,"<="&45930) -> 0 | M5: =SUMIFS('Atendimentos à Receber'!$R:$R,'Atendimentos à Receber'!$V:$V,">="&45931,'Atendimentos à Receber'!$V:$V,"<="&45961) -> 0 | N5: =SUMIFS('Atendimentos à Receber'!$R:$R,'Atendimentos à Receber'!$V:$V,">="&45962,'Atendimentos à Receber'!$V:$V,"<="&45991) -> 0 | O5: =SUMIFS('Atendimentos à Receber'!$R:$R,'Atendimentos à Receber'!$V:$V,">="&45992,'Atendimentos à Receber'!$V:$V,"<="&46022) -> 0
B6: Outros Recebimentos | C6: =SUM(D6:O6) -> 0 | D6: =SUMIFS('Outras Contas à Receber'!$G:$G,'Outras Contas à Receber'!$I:$I,">="&45658,'Outras Contas à Receber'!$I:$I,"<="&45688) -> 0 | E6: =SUMIFS('Outras Contas à Receber'!$G:$G,'Outras Contas à Receber'!$I:$I,">="&45689,'Outras Contas à Receber'!$I:$I,"<="&45716) -> 0 | F6: =SUMIFS('Outras Contas à Receber'!$G:$G,'Outras Contas à Receber'!$I:$I,">="&45717,'Outras Contas à Receber'!$I:$I,"<="&45747) -> 0 | G6: =SUMIFS('Outras Contas à Receber'!$G:$G,'Outras Contas à Receber'!$I:$I,">="&45748,'Outras Contas à Receber'!$I:$I,"<="&45777) -> 0 | H6: =SUMIFS('Outras Contas à Receber'!$G:$G,'Outras Contas à Receber'!$I:$I,">="&45778,'Outras Contas à Receber'!$I:$I,"<="&45808) -> 0 | I6: =SUMIFS('Outras Contas à Receber'!$G:$G,'Outras Contas à Receber'!$I:$I,">="&45809,'Outras Contas à Receber'!$I:$I,"<="&45838) -> 0 | J6: =SUMIFS('Outras Contas à Receber'!$G:$G,'Outras Contas à Receber'!$I:$I,">="&45839,'Outras Contas à Receber'!$I:$I,"<="&45869) -> 0 | K6: =SUMIFS('Outras Contas à Receber'!$G:$G,'Outras Contas à Receber'!$I:$I,">="&45870,'Outras Contas à Receber'!$I:$I,"<="&45900) -> 0 | L6: =SUMIFS('Outras Contas à Receber'!$G:$G,'Outras Contas à Receber'!$I:$I,">="&45901,'Outras Contas à Receber'!$I:$I,"<="&45930) -> 0 | M6: =SUMIFS('Outras Contas à Receber'!$G:$G,'Outras Contas à Receber'!$I:$I,">="&45931,'Outras Contas à Receber'!$I:$I,"<="&45961) -> 0 | N6: =SUMIFS('Outras Contas à Receber'!$G:$G,'Outras Contas à Receber'!$I:$I,">="&45962,'Outras Contas à Receber'!$I:$I,"<="&45991) -> 0 | O6: =SUMIFS('Outras Contas à Receber'!$G:$G,'Outras Contas à Receber'!$I:$I,">="&45992,'Outras Contas à Receber'!$I:$I,"<="&46022) -> 0
B7: Total Custos | C7: =SUM(D7:O7) -> 0 | D7: =SUM(D8:D9) -> 0 | E7: =SUM(E8:E9) -> 0 | F7: =SUM(F8:F9) -> 0 | G7: =SUM(G8:G9) -> 0 | H7: =SUM(H8:H9) -> 0 | I7: =SUM(I8:I9) -> 0 | J7: =SUM(J8:J9) -> 0 | K7: =SUM(K8:K9) -> 0 | ... O7: =SUM(O8:O9) -> 0
B8: Custos | C8: =SUM(D8:O8) -> 0 | D8: =-SUMIFS('Contas à Pagar'!$G:$G,'Contas à Pagar'!$H:$H,">="&45658,'Contas à Pagar'!$H:$H,"<="&45688,'Contas à Pagar'!B:B,"Conta da clínica",'Contas à Pagar'!E:E,"Quitado") -> 0 | E8: =-SUMIFS('Contas à Pagar'!$G:$G,'Contas à Pagar'!$H:$H,">="&45689,'Contas à Pagar'!$H:$H,"<="&45716,'Contas à Pagar'!B:B,"Conta da clínica",'Contas à Pagar'!E:E,"Quitado") -> 0 | F8: =-SUMIFS('Contas à Pagar'!$G:$G,'Contas à Pagar'!$H:$H,">="&45717,'Contas à Pagar'!$H:$H,"<="&45747,'Contas à Pagar'!B:B,"Conta da clínica",'Contas à Pagar'!E:E,"Quitado") -> 0 | G8: =-SUMIFS('Contas à Pagar'!$G:$G,'Contas à Pagar'!$H:$H,">="&45748,'Contas à Pagar'!$H:$H,"<="&45777,'Contas à Pagar'!B:B,"Conta da clínica",'Contas à Pagar'!E:E,"Quitado") -> 0 | H8: =-SUMIFS('Contas à Pagar'!$G:$G,'Contas à Pagar'!$H:$H,">="&45778,'Contas à Pagar'!$H:$H,"<="&45808,'Contas à Pagar'!B:B,"Conta da clínica",'Contas à Pagar'!E:E,"Quitado") -> 0 | I8: =-SUMIFS('Contas à Pagar'!$G:$G,'Contas à Pagar'!$H:$H,">="&45809,'Contas à Pagar'!$H:$H,"<="&45838,'Contas à Pagar'!B:B,"Conta da clínica",'Contas à Pagar'!E:E,"Quitado") -> 0 | J8: =-SUMIFS('Contas à Pagar'!$G:$G,'Contas à Pagar'!$H:$H,">="&45839,'Contas à Pagar'!$H:$H,"<="&45869,'Contas à Pagar'!B:B,"Conta da clínica",'Contas à Pagar'!E:E,"Quitado") -> 0 | K8: =-SUMIFS('Contas à Pagar'!$G:$G,'Contas à Pagar'!$H:$H,">="&45870,'Contas à Pagar'!$H:$H,"<="&45900,'Contas à Pagar'!B:B,"Conta da clínica",'Contas à Pagar'!E:E,"Quitado") -> 0 | L8: =-SUMIFS('Contas à Pagar'!$G:$G,'Contas à Pagar'!$H:$H,">="&45901,'Contas à Pagar'!$H:$H,"<="&45930,'Contas à Pagar'!B:B,"Conta da clínica",'Contas à Pagar'!E:E,"Quitado") -> 0 | M8: =-SUMIFS('Contas à Pagar'!$G:$G,'Contas à Pagar'!$H:$H,">="&45931,'Contas à Pagar'!$H:$H,"<="&45961,'Contas à Pagar'!B:B,"Conta da clínica",'Contas à Pagar'!E:E,"Quitado") -> 0 | N8: =-SUMIFS('Contas à Pagar'!$G:$G,'Contas à Pagar'!$H:$H,">="&45962,'Contas à Pagar'!$H:$H,"<="&45991,'Contas à Pagar'!B:B,"Conta da clínica",'Contas à Pagar'!E:E,"Quitado") -> 0 | O8: =-SUMIFS('Contas à Pagar'!$G:$G,'Contas à Pagar'!$H:$H,">="&45992,'Contas à Pagar'!$H:$H,"<="&46022,'Contas à Pagar'!B:B,"Conta da clínica",'Contas à Pagar'!E:E,"Quitado") -> 0
B9: Comissões | C9: =SUM(D9:O9) -> 0 | D9: =-SUMIFS('Atendimentos à Receber'!$T:$T,'Atendimentos à Receber'!$V:$V,">="&45658,'Atendimentos à Receber'!$V:$V,"<="&45688) -> 0 | E9: =-SUMIFS('Atendimentos à Receber'!$T:$T,'Atendimentos à Receber'!$V:$V,">="&45689,'Atendimentos à Receber'!$V:$V,"<="&45716) -> 0 | F9: =-SUMIFS('Atendimentos à Receber'!$T:$T,'Atendimentos à Receber'!$V:$V,">="&45717,'Atendimentos à Receber'!$V:$V,"<="&45748) -> 0 | G9: =-SUMIFS('Atendimentos à Receber'!$T:$T,'Atendimentos à Receber'!$V:$V,">="&45748,'Atendimentos à Receber'!$V:$V,"<="&45777) -> 0 | H9: =-SUMIFS('Atendimentos à Receber'!$T:$T,'Atendimentos à Receber'!$V:$V,">="&45778,'Atendimentos à Receber'!$V:$V,"<="&45808) -> 0 | I9: =-SUMIFS('Atendimentos à Receber'!$T:$T,'Atendimentos à Receber'!$V:$V,">="&45809,'Atendimentos à Receber'!$V:$V,"<="&45838) -> 0 | J9: =-SUMIFS('Atendimentos à Receber'!$T:$T,'Atendimentos à Receber'!$V:$V,">="&45839,'Atendimentos à Receber'!$V:$V,"<="&45869) -> 0 | K9: =-SUMIFS('Atendimentos à Receber'!$T:$T,'Atendimentos à Receber'!$V:$V,">="&45870,'Atendimentos à Receber'!$V:$V,"<="&45900) -> 0 | L9: =-SUMIFS('Atendimentos à Receber'!$T:$T,'Atendimentos à Receber'!$V:$V,">="&45901,'Atendimentos à Receber'!$V:$V,"<="&45930) -> 0 | M9: =-SUMIFS('Atendimentos à Receber'!$T:$T,'Atendimentos à Receber'!$V:$V,">="&45931,'Atendimentos à Receber'!$V:$V,"<="&45961) -> 0 | N9: =-SUMIFS('Atendimentos à Receber'!$T:$T,'Atendimentos à Receber'!$V:$V,">="&45962,'Atendimentos à Receber'!$V:$V,"<="&45991) -> 0 | O9: =-SUMIFS('Atendimentos à Receber'!$T:$T,'Atendimentos à Receber'!$V:$V,">="&45992,'Atendimentos à Receber'!$V:$V,"<="&46022) -> 0
B10: Lucro Líquido | C10: =SUM(D10:O10) -> 0 | D10: =D4+D7 -> 0 | E10: =E4+E7 -> 0 | F10: =F4+F7 -> 0 | G10: =G4+G7 -> 0 | H10: =H4+H7 -> 0 | I10: =I4+I7 -> 0 | J10: =J4+J7 -> 0 | K10: =K4+K7 -> 0 | ... O10: =O4+O7 -> 0
B12: Fluxo De Caixa | D12: =C13+D10 -> 0 | E12: =D12+E10 -> 0 | F12: =E12+F10 -> 0 | G12: =F12+G10 -> 0 | H12: =G12+H10 -> 0 | I12: =H12+I10 -> 0 | J12: =I12+J10 -> 0 | K12: =J12+K10 -> 0 | L12: =K12+L10 -> 0 | ... O12: =N12+O10 -> 0
B13: Caixa Inicial | C13: 0
B16: Resultados em Aberto
C18: Acumulado no Ano | D18: 45292 | E18: 45323 | F18: 45352 | G18: 45383 | H18: 45413 | I18: 45444 | J18: 45474 | K18: 45505 | L18: 45536 | M18: 45566 | N18: 45597 | O18: 45627
B19: Faturamento em Aberto | C19: =SUM(D19:O19) -> 0 | D19: =SUM(D20:D21) -> 0 | E19: =SUM(E20:E21) -> 0 | F19: =SUM(F20:F21) -> 0 | G19: =SUM(G20:G21) -> 0 | H19: =SUM(H20:H21) -> 0 | I19: =SUM(I20:I21) -> 0 | J19: =SUM(J20:J21) -> 0 | K19: =SUM(K20:K21) -> 0 | ... O19: =SUM(O20:O21) -> 0
B20: Recebimento Pacientes | C20: =SUM(D20:O20) -> 0 | D20: =SUMIFS('Atendimentos à Receber'!$S:$S,'Atendimentos à Receber'!$V:$V,">="&45658,'Atendimentos à Receber'!$V:$V,"<="&45688)-SUMIFS('Atendimentos à Receber'!$R:$R,'Atendimentos à Receber'!$V:$V,">="&45658,'Atendimentos à Receber'!$V:$V,"<="&45688) -> 0 | E20: =SUMIFS('Atendimentos à Receber'!$S:$S,'Atendimentos à Receber'!$V:$V,">="&45689,'Atendimentos à Receber'!$V:$V,"<="&45716)-SUMIFS('Atendimentos à Receber'!$R:$R,'Atendimentos à Receber'!$V:$V,">="&45689,'Atendimentos à Receber'!$V:$V,"<="&45716) -> 0 | F20: =SUMIFS('Atendimentos à Receber'!$S:$S,'Atendimentos à Receber'!$V:$V,">="&45717,'Atendimentos à Receber'!$V:$V,"<="&45748)-SUMIFS('Atendimentos à Receber'!$R:$R,'Atendimentos à Receber'!$V:$V,">="&45717,'Atendimentos à Receber'!$V:$V,"<="&45748) -> 0 | G20: =SUMIFS('Atendimentos à Receber'!$S:$S,'Atendimentos à Receber'!$V:$V,">="&45748,'Atendimentos à Receber'!$V:$V,"<="&45777)-SUMIFS('Atendimentos à Receber'!$R:$R,'Atendimentos à Receber'!$V:$V,">="&45748,'Atendimentos à Receber'!$V:$V,"<="&45777) -> 0 | H20: =SUMIFS('Atendimentos à Receber'!$S:$S,'Atendimentos à Receber'!$V:$V,">="&45778,'Atendimentos à Receber'!$V:$V,"<="&45808)-SUMIFS('Atendimentos à Receber'!$R:$R,'Atendimentos à Receber'!$V:$V,">="&45778,'Atendimentos à Receber'!$V:$V,"<="&45808) -> 0 | I20: =SUMIFS('Atendimentos à Receber'!$S:$S,'Atendimentos à Receber'!$V:$V,">="&45809,'Atendimentos à Receber'!$V:$V,"<="&45838)-SUMIFS('Atendimentos à Receber'!$R:$R,'Atendimentos à Receber'!$V:$V,">="&45809,'Atendimentos à Receber'!$V:$V,"<="&45838) -> 0 | J20: =SUMIFS('Atendimentos à Receber'!$S:$S,'Atendimentos à Receber'!$V:$V,">="&45839,'Atendimentos à Receber'!$V:$V,"<="&45869)-SUMIFS('Atendimentos à Receber'!$R:$R,'Atendimentos à Receber'!$V:$V,">="&45839,'Atendimentos à Receber'!$V:$V,"<="&45869) -> 0 | K20: =SUMIFS('Atendimentos à Receber'!$S:$S,'Atendimentos à Receber'!$V:$V,">="&45870,'Atendimentos à Receber'!$V:$V,"<="&45900)-SUMIFS('Atendimentos à Receber'!$R:$R,'Atendimentos à Receber'!$V:$V,">="&45870,'Atendimentos à Receber'!$V:$V,"<="&45900) -> 0 | L20: =SUMIFS('Atendimentos à Receber'!$S:$S,'Atendimentos à Receber'!$V:$V,">="&45901,'Atendimentos à Receber'!$V:$V,"<="&45930)-SUMIFS('Atendimentos à Receber'!$R:$R,'Atendimentos à Receber'!$V:$V,">="&45901,'Atendimentos à Receber'!$V:$V,"<="&45930) -> 0 | M20: =SUMIFS('Atendimentos à Receber'!$S:$S,'Atendimentos à Receber'!$V:$V,">="&45931,'Atendimentos à Receber'!$V:$V,"<="&45961)-SUMIFS('Atendimentos à Receber'!$R:$R,'Atendimentos à Receber'!$V:$V,">="&45931,'Atendimentos à Receber'!$V:$V,"<="&45961) -> 0 | N20: =SUMIFS('Atendimentos à Receber'!$S:$S,'Atendimentos à Receber'!$V:$V,">="&45962,'Atendimentos à Receber'!$V:$V,"<="&45991)-SUMIFS('Atendimentos à Receber'!$R:$R,'Atendimentos à Receber'!$V:$V,">="&45962,'Atendimentos à Receber'!$V:$V,"<="&45991) -> 0 | O20: =SUMIFS('Atendimentos à Receber'!$S:$S,'Atendimentos à Receber'!$V:$V,">="&45992,'Atendimentos à Receber'!$V:$V,"<="&46022)-SUMIFS('Atendimentos à Receber'!$R:$R,'Atendimentos à Receber'!$V:$V,">="&45992,'Atendimentos à Receber'!$V:$V,"<="&46022) -> 0
B21: Outros Recebimentos | C21: =SUM(D21:O21) -> 0 | D21: =SUMIFS('Outras Contas à Receber'!$H:$H,'Outras Contas à Receber'!$I:$I,">="&45658,'Outras Contas à Receber'!$I:$I,"<="&45688)-SUMIFS('Outras Contas à Receber'!$G:$G,'Outras Contas à Receber'!$I:$I,">="&45658,'Outras Contas à Receber'!$I:$I,"<="&45688) -> 0 | E21: =SUMIFS('Outras Contas à Receber'!$H:$H,'Outras Contas à Receber'!$I:$I,">="&45689,'Outras Contas à Receber'!$I:$I,"<="&45716)-SUMIFS('Outras Contas à Receber'!$G:$G,'Outras Contas à Receber'!$I:$I,">="&45689,'Outras Contas à Receber'!$I:$I,"<="&45716) -> 0 | F21: =SUMIFS('Outras Contas à Receber'!$H:$H,'Outras Contas à Receber'!$I:$I,">="&45717,'Outras Contas à Receber'!$I:$I,"<="&45747)-SUMIFS('Outras Contas à Receber'!$G:$G,'Outras Contas à Receber'!$I:$I,">="&45717,'Outras Contas à Receber'!$I:$I,"<="&45747) -> 0 | G21: =SUMIFS('Outras Contas à Receber'!$H:$H,'Outras Contas à Receber'!$I:$I,">="&45748,'Outras Contas à Receber'!$I:$I,"<="&45777)-SUMIFS('Outras Contas à Receber'!$G:$G,'Outras Contas à Receber'!$I:$I,">="&45748,'Outras Contas à Receber'!$I:$I,"<="&45777) -> 0 | H21: =SUMIFS('Outras Contas à Receber'!$H:$H,'Outras Contas à Receber'!$I:$I,">="&45778,'Outras Contas à Receber'!$I:$I,"<="&45808)-SUMIFS('Outras Contas à Receber'!$G:$G,'Outras Contas à Receber'!$I:$I,">="&45778,'Outras Contas à Receber'!$I:$I,"<="&45808) -> 0 | I21: =SUMIFS('Outras Contas à Receber'!$H:$H,'Outras Contas à Receber'!$I:$I,">="&45809,'Outras Contas à Receber'!$I:$I,"<="&45838)-SUMIFS('Outras Contas à Receber'!$G:$G,'Outras Contas à Receber'!$I:$I,">="&45809,'Outras Contas à Receber'!$I:$I,"<="&45838) -> 0 | J21: =SUMIFS('Outras Contas à Receber'!$H:$H,'Outras Contas à Receber'!$I:$I,">="&45839,'Outras Contas à Receber'!$I:$I,"<="&45869)-SUMIFS('Outras Contas à Receber'!$G:$G,'Outras Contas à Receber'!$I:$I,">="&45839,'Outras Contas à Receber'!$I:$I,"<="&45869) -> 0 | K21: =SUMIFS('Outras Contas à Receber'!$H:$H,'Outras Contas à Receber'!$I:$I,">="&45870,'Outras Contas à Receber'!$I:$I,"<="&45900)-SUMIFS('Outras Contas à Receber'!$G:$G,'Outras Contas à Receber'!$I:$I,">="&45870,'Outras Contas à Receber'!$I:$I,"<="&45900) -> 0 | L21: =SUMIFS('Outras Contas à Receber'!$H:$H,'Outras Contas à Receber'!$I:$I,">="&45901,'Outras Contas à Receber'!$I:$I,"<="&45930)-SUMIFS('Outras Contas à Receber'!$G:$G,'Outras Contas à Receber'!$I:$I,">="&45901,'Outras Contas à Receber'!$I:$I,"<="&45930) -> 0 | M21: =SUMIFS('Outras Contas à Receber'!$H:$H,'Outras Contas à Receber'!$I:$I,">="&45931,'Outras Contas à Receber'!$I:$I,"<="&45961)-SUMIFS('Outras Contas à Receber'!$G:$G,'Outras Contas à Receber'!$I:$I,">="&45931,'Outras Contas à Receber'!$I:$I,"<="&45961) -> 0 | N21: =SUMIFS('Outras Contas à Receber'!$H:$H,'Outras Contas à Receber'!$I:$I,">="&45962,'Outras Contas à Receber'!$I:$I,"<="&45991)-SUMIFS('Outras Contas à Receber'!$G:$G,'Outras Contas à Receber'!$I:$I,">="&45962,'Outras Contas à Receber'!$I:$I,"<="&45991) -> 0 | O21: =SUMIFS('Outras Contas à Receber'!$H:$H,'Outras Contas à Receber'!$I:$I,">="&45992,'Outras Contas à Receber'!$I:$I,"<="&46022)-SUMIFS('Outras Contas à Receber'!$G:$G,'Outras Contas à Receber'!$I:$I,">="&45992,'Outras Contas à Receber'!$I:$I,"<="&46022) -> 0
B22: Custos em Aberto | C22: =SUM(D22:O22) -> 0 | D22: =SUM(D23:D24) -> 0 | E22: =SUM(E23:E24) -> 0 | F22: =SUM(F23:F24) -> 0 | G22: =SUM(G23:G24) -> 0 | H22: =SUM(H23:H24) -> 0 | I22: =SUM(I23:I24) -> 0 | J22: =SUM(J23:J24) -> 0 | K22: =SUM(K23:K24) -> 0 | ... O22: =SUM(O23:O24) -> 0
B23: Custos | C23: =SUM(D23:O23) -> 0 | D23: =-SUMIFS('Contas à Pagar'!$G:$G,'Contas à Pagar'!$H:$H,">="&45658,'Contas à Pagar'!$H:$H,"<="&45688,'Contas à Pagar'!B:B,"Conta da clínica",'Contas à Pagar'!E:E,"Em Aberto") -> 0 | E23: =-SUMIFS('Contas à Pagar'!$G:$G,'Contas à Pagar'!$H:$H,">="&45689,'Contas à Pagar'!$H:$H,"<="&45716,'Contas à Pagar'!B:B,"Conta da clínica",'Contas à Pagar'!E:E,"Em Aberto") -> 0 | F23: =-SUMIFS('Contas à Pagar'!$G:$G,'Contas à Pagar'!$H:$H,">="&45717,'Contas à Pagar'!$H:$H,"<="&45747,'Contas à Pagar'!B:B,"Conta da clínica",'Contas à Pagar'!E:E,"Em Aberto") -> 0 | G23: =-SUMIFS('Contas à Pagar'!$G:$G,'Contas à Pagar'!$H:$H,">="&45748,'Contas à Pagar'!$H:$H,"<="&45777,'Contas à Pagar'!B:B,"Conta da clínica",'Contas à Pagar'!E:E,"Em Aberto") -> 0 | H23: =-SUMIFS('Contas à Pagar'!$G:$G,'Contas à Pagar'!$H:$H,">="&45778,'Contas à Pagar'!$H:$H,"<="&45808,'Contas à Pagar'!B:B,"Conta da clínica",'Contas à Pagar'!E:E,"Em Aberto") -> 0 | I23: =-SUMIFS('Contas à Pagar'!$G:$G,'Contas à Pagar'!$H:$H,">="&45809,'Contas à Pagar'!$H:$H,"<="&45838,'Contas à Pagar'!B:B,"Conta da clínica",'Contas à Pagar'!E:E,"Em Aberto") -> 0 | J23: =-SUMIFS('Contas à Pagar'!$G:$G,'Contas à Pagar'!$H:$H,">="&45839,'Contas à Pagar'!$H:$H,"<="&45869,'Contas à Pagar'!B:B,"Conta da clínica",'Contas à Pagar'!E:E,"Em Aberto") -> 0 | K23: =-SUMIFS('Contas à Pagar'!$G:$G,'Contas à Pagar'!$H:$H,">="&45870,'Contas à Pagar'!$H:$H,"<="&45900,'Contas à Pagar'!B:B,"Conta da clínica",'Contas à Pagar'!E:E,"Em Aberto") -> 0 | L23: =-SUMIFS('Contas à Pagar'!$G:$G,'Contas à Pagar'!$H:$H,">="&45901,'Contas à Pagar'!$H:$H,"<="&45930,'Contas à Pagar'!B:B,"Conta da clínica",'Contas à Pagar'!E:E,"Em Aberto") -> 0 | M23: =-SUMIFS('Contas à Pagar'!$G:$G,'Contas à Pagar'!$H:$H,">="&45931,'Contas à Pagar'!$H:$H,"<="&45961,'Contas à Pagar'!B:B,"Conta da clínica",'Contas à Pagar'!E:E,"Em Aberto") -> 0 | N23: =-SUMIFS('Contas à Pagar'!$G:$G,'Contas à Pagar'!$H:$H,">="&45962,'Contas à Pagar'!$H:$H,"<="&45991,'Contas à Pagar'!B:B,"Conta da clínica",'Contas à Pagar'!E:E,"Em Aberto") -> 0 | O23: =-SUMIFS('Contas à Pagar'!$G:$G,'Contas à Pagar'!$H:$H,">="&45992,'Contas à Pagar'!$H:$H,"<="&46022,'Contas à Pagar'!B:B,"Conta da clínica",'Contas à Pagar'!E:E,"Em Aberto") -> 0
B24: Comissões | C24: =SUM(D24:O24) -> 0 | D24: =-SUMIFS('Atendimentos à Receber'!$U:$U,'Atendimentos à Receber'!$V:$V,">="&45658,'Atendimentos à Receber'!$V:$V,"<="&45688)+SUMIFS('Atendimentos à Receber'!$T:$T,'Atendimentos à Receber'!$V:$V,">="&45658,'Atendimentos à Receber'!$V:$V,"<="&45688) -> 0 | E24: =-SUMIFS('Atendimentos à Receber'!$U:$U,'Atendimentos à Receber'!$V:$V,">="&45689,'Atendimentos à Receber'!$V:$V,"<="&45716)+SUMIFS('Atendimentos à Receber'!$T:$T,'Atendimentos à Receber'!$V:$V,">="&45689,'Atendimentos à Receber'!$V:$V,"<="&45716) -> 0 | F24: =-SUMIFS('Atendimentos à Receber'!$U:$U,'Atendimentos à Receber'!$V:$V,">="&45717,'Atendimentos à Receber'!$V:$V,"<="&45748)+SUMIFS('Atendimentos à Receber'!$T:$T,'Atendimentos à Receber'!$V:$V,">="&45717,'Atendimentos à Receber'!$V:$V,"<="&45748) -> 0 | G24: =-SUMIFS('Atendimentos à Receber'!$U:$U,'Atendimentos à Receber'!$V:$V,">="&45748,'Atendimentos à Receber'!$V:$V,"<="&45777)+SUMIFS('Atendimentos à Receber'!$T:$T,'Atendimentos à Receber'!$V:$V,">="&45748,'Atendimentos à Receber'!$V:$V,"<="&45777) -> 0 | H24: =-SUMIFS('Atendimentos à Receber'!$U:$U,'Atendimentos à Receber'!$V:$V,">="&45778,'Atendimentos à Receber'!$V:$V,"<="&45808)+SUMIFS('Atendimentos à Receber'!$T:$T,'Atendimentos à Receber'!$V:$V,">="&45778,'Atendimentos à Receber'!$V:$V,"<="&45808) -> 0 | I24: =-SUMIFS('Atendimentos à Receber'!$U:$U,'Atendimentos à Receber'!$V:$V,">="&45809,'Atendimentos à Receber'!$V:$V,"<="&45838)+SUMIFS('Atendimentos à Receber'!$T:$T,'Atendimentos à Receber'!$V:$V,">="&45809,'Atendimentos à Receber'!$V:$V,"<="&45838) -> 0 | J24: =-SUMIFS('Atendimentos à Receber'!$U:$U,'Atendimentos à Receber'!$V:$V,">="&45839,'Atendimentos à Receber'!$V:$V,"<="&45869)+SUMIFS('Atendimentos à Receber'!$T:$T,'Atendimentos à Receber'!$V:$V,">="&45839,'Atendimentos à Receber'!$V:$V,"<="&45869) -> 0 | K24: =-SUMIFS('Atendimentos à Receber'!$U:$U,'Atendimentos à Receber'!$V:$V,">="&45870,'Atendimentos à Receber'!$V:$V,"<="&45900)+SUMIFS('Atendimentos à Receber'!$T:$T,'Atendimentos à Receber'!$V:$V,">="&45870,'Atendimentos à Receber'!$V:$V,"<="&45900) -> 0 | L24: =-SUMIFS('Atendimentos à Receber'!$U:$U,'Atendimentos à Receber'!$V:$V,">="&45901,'Atendimentos à Receber'!$V:$V,"<="&45930)+SUMIFS('Atendimentos à Receber'!$T:$T,'Atendimentos à Receber'!$V:$V,">="&45901,'Atendimentos à Receber'!$V:$V,"<="&45930) -> 0 | M24: =-SUMIFS('Atendimentos à Receber'!$U:$U,'Atendimentos à Receber'!$V:$V,">="&45931,'Atendimentos à Receber'!$V:$V,"<="&45961)+SUMIFS('Atendimentos à Receber'!$T:$T,'Atendimentos à Receber'!$V:$V,">="&45931,'Atendimentos à Receber'!$V:$V,"<="&45961) -> 0 | N24: =-SUMIFS('Atendimentos à Receber'!$U:$U,'Atendimentos à Receber'!$V:$V,">="&45962,'Atendimentos à Receber'!$V:$V,"<="&45991)+SUMIFS('Atendimentos à Receber'!$T:$T,'Atendimentos à Receber'!$V:$V,">="&45962,'Atendimentos à Receber'!$V:$V,"<="&45991) -> 0 | O24: =-SUMIFS('Atendimentos à Receber'!$U:$U,'Atendimentos à Receber'!$V:$V,">="&45992,'Atendimentos à Receber'!$V:$V,"<="&46022)+SUMIFS('Atendimentos à Receber'!$T:$T,'Atendimentos à Receber'!$V:$V,">="&45992,'Atendimentos à Receber'!$V:$V,"<="&46022) -> 0
B25: Lucro em Aberto | C25: =SUM(D25:O25) -> 0 | D25: =D19+D22 -> 0 | E25: =E19+E22 -> 0 | F25: =F19+F22 -> 0 | G25: =G19+G22 -> 0 | H25: =H19+H22 -> 0 | I25: =I19+I22 -> 0 | J25: =J19+J22 -> 0 | K25: =K19+K22 -> 0 | ... O25: =O19+O22 -> 0

Sheet Resultado Profissional
B1: Resultados do Profissional
C3: Acumulado no Ano | D3: 45292 | E3: 45323 | F3: 45352 | G3: 45383 | H3: 45413 | I3: 45444 | J3: 45474 | K3: 45505 | L3: 45536 | M3: 45566 | N3: 45597 | O3: 45627
B4: Faturamento | C4: =SUM(D4:O4) -> 0 | D4: =SUM(D5:D6) -> 0 | E4: =SUM(E5:E6) -> 0 | F4: =SUM(F5:F6) -> 0 | G4: =SUM(G5:G6) -> 0 | H4: =SUM(H5:H6) -> 0 | I4: =SUM(I5:I6) -> 0 | J4: =SUM(J5:J6) -> 0 | K4: =SUM(K5:K6) -> 0 | ... O4: =SUM(O5:O6) -> 0
B5: Recebimento Pacientes | C5: =SUM(D5:O5) -> 0 | D5: =SUMIFS('Atendimentos à Receber'!$R:$R,'Atendimentos à Receber'!$V:$V,">="&45658,'Atendimentos à Receber'!$V:$V,"<="&45688,'Atendimentos à Receber'!$E:$E,$B$3) -> 0 | E5: =SUMIFS('Atendimentos à Receber'!$R:$R,'Atendimentos à Receber'!$V:$V,">="&45689,'Atendimentos à Receber'!$V:$V,"<="&45716,'Atendimentos à Receber'!$E:$E,$B$3) -> 0 | F5: =SUMIFS('Atendimentos à Receber'!$R:$R,'Atendimentos à Receber'!$V:$V,">="&45717,'Atendimentos à Receber'!$V:$V,"<="&45748,'Atendimentos à Receber'!$E:$E,$B$3) -> 0 | G5: =SUMIFS('Atendimentos à Receber'!$R:$R,'Atendimentos à Receber'!$V:$V,">="&45748,'Atendimentos à Receber'!$V:$V,"<="&45777,'Atendimentos à Receber'!$E:$E,$B$3) -> 0 | H5: =SUMIFS('Atendimentos à Receber'!$R:$R,'Atendimentos à Receber'!$V:$V,">="&45778,'Atendimentos à Receber'!$V:$V,"<="&45808,'Atendimentos à Receber'!$E:$E,$B$3) -> 0 | I5: =SUMIFS('Atendimentos à Receber'!$R:$R,'Atendimentos à Receber'!$V:$V,">="&45809,'Atendimentos à Receber'!$V:$V,"<="&45838,'Atendimentos à Receber'!$E:$E,$B$3) -> 0 | J5: =SUMIFS('Atendimentos à Receber'!$R:$R,'Atendimentos à Receber'!$V:$V,">="&45839,'Atendimentos à Receber'!$V:$V,"<="&45869,'Atendimentos à Receber'!$E:$E,$B$3) -> 0 | K5: =SUMIFS('Atendimentos à Receber'!$R:$R,'Atendimentos à Receber'!$V:$V,">="&45870,'Atendimentos à Receber'!$V:$V,"<="&45900,'Atendimentos à Receber'!$E:$E,$B$3) -> 0 | L5: =SUMIFS('Atendimentos à Receber'!$R:$R,'Atendimentos à Receber'!$V:$V,">="&45901,'Atendimentos à Receber'!$V:$V,"<="&45930,'Atendimentos à Receber'!$E:$E,$B$3) -> 0 | M5: =SUMIFS('Atendimentos à Receber'!$R:$R,'Atendimentos à Receber'!$V:$V,">="&45931,'Atendimentos à Receber'!$V:$V,"<="&45961,'Atendimentos à Receber'!$E:$E,$B$3) -> 0 | N5: =SUMIFS('Atendimentos à Receber'!$R:$R,'Atendimentos à Receber'!$V:$V,">="&45962,'Atendimentos à Receber'!$V:$V,"<="&45991,'Atendimentos à Receber'!$E:$E,$B$3) -> 0 | O5: =SUMIFS('Atendimentos à Receber'!$R:$R,'Atendimentos à Receber'!$V:$V,">="&45992,'Atendimentos à Receber'!$V:$V,"<="&46022,'Atendimentos à Receber'!$E:$E,$B$3) -> 0
B6: Outros Recebimentos | C6: =SUM(D6:O6) -> 0 | D6: =SUMIFS('Outras Contas à Receber'!$G:$G,'Outras Contas à Receber'!$I:$I,">="&45658,'Outras Contas à Receber'!$I:$I,"<="&45688,'Outras Contas à Receber'!$B:$B,$B$3) -> 0 | E6: =SUMIFS('Outras Contas à Receber'!$G:$G,'Outras Contas à Receber'!$I:$I,">="&45689,'Outras Contas à Receber'!$I:$I,"<="&45716,'Outras Contas à Receber'!$B:$B,$B$3) -> 0 | F6: =SUMIFS('Outras Contas à Receber'!$G:$G,'Outras Contas à Receber'!$I:$I,">="&45717,'Outras Contas à Receber'!$I:$I,"<="&45747,'Outras Contas à Receber'!$B:$B,$B$3) -> 0 | G6: =SUMIFS('Outras Contas à Receber'!$G:$G,'Outras Contas à Receber'!$I:$I,">="&45748,'Outras Contas à Receber'!$I:$I,"<="&45777,'Outras Contas à Receber'!$B:$B,$B$3) -> 0 | H6: =SUMIFS('Outras Contas à Receber'!$G:$G,'Outras Contas à Receber'!$I:$I,">="&45778,'Outras Contas à Receber'!$I:$I,"<="&45808,'Outras Contas à Receber'!$B:$B,$B$3) -> 0 | I6: =SUMIFS('Outras Contas à Receber'!$G:$G,'Outras Contas à Receber'!$I:$I,">="&45809,'Outras Contas à Receber'!$I:$I,"<="&45838,'Outras Contas à Receber'!$B:$B,$B$3) -> 0 | J6: =SUMIFS('Outras Contas à Receber'!$G:$G,'Outras Contas à Receber'!$I:$I,">="&45839,'Outras Contas à Receber'!$I:$I,"<="&45869,'Outras Contas à Receber'!$B:$B,$B$3) -> 0 | K6: =SUMIFS('Outras Contas à Receber'!$G:$G,'Outras Contas à Receber'!$I:$I,">="&45870,'Outras Contas à Receber'!$I:$I,"<="&45900,'Outras Contas à Receber'!$B:$B,$B$3) -> 0 | L6: =SUMIFS('Outras Contas à Receber'!$G:$G,'Outras Contas à Receber'!$I:$I,">="&45901,'Outras Contas à Receber'!$I:$I,"<="&45930,'Outras Contas à Receber'!$B:$B,$B$3) -> 0 | M6: =SUMIFS('Outras Contas à Receber'!$G:$G,'Outras Contas à Receber'!$I:$I,">="&45931,'Outras Contas à Receber'!$I:$I,"<="&45961,'Outras Contas à Receber'!$B:$B,$B$3) -> 0 | N6: =SUMIFS('Outras Contas à Receber'!$G:$G,'Outras Contas à Receber'!$I:$I,">="&45962,'Outras Contas à Receber'!$I:$I,"<="&45991,'Outras Contas à Receber'!$B:$B,$B$3) -> 0 | O6: =SUMIFS('Outras Contas à Receber'!$G:$G,'Outras Contas à Receber'!$I:$I,">="&45992,'Outras Contas à Receber'!$I:$I,"<="&46022,'Outras Contas à Receber'!$B:$B,$B$3) -> 0
B7: Total Custos | C7: =SUM(D7:O7) -> 0 | D7: =SUM(D8:D9) -> 0 | E7: =SUM(E8:E9) -> 0 | F7: =SUM(F8:F9) -> 0 | G7: =SUM(G8:G9) -> 0 | H7: =SUM(H8:H9) -> 0 | I7: =SUM(I8:I9) -> 0 | J7: =SUM(J8:J9) -> 0 | K7: =SUM(K8:K9) -> 0 | ... O7: =SUM(O8:O9) -> 0
B8: Custos | C8: =SUM(D8:O8) -> 0 | D8: =-SUMIFS('Contas à Pagar'!$G:$G,'Contas à Pagar'!$H:$H,">="&45658,'Contas à Pagar'!$H:$H,"<="&45688,'Contas à Pagar'!B:B,"Conta da clínica",'Contas à Pagar'!E:E,"Quitado",'Contas à Pagar'!B:B,$B$3) -> 0 | E8: =-SUMIFS('Contas à Pagar'!$G:$G,'Contas à Pagar'!$H:$H,">="&45689,'Contas à Pagar'!$H:$H,"<="&45716,'Contas à Pagar'!B:B,"Conta da clínica",'Contas à Pagar'!E:E,"Quitado",'Contas à Pagar'!B:B,$B$3) -> 0 | F8: =-SUMIFS('Contas à Pagar'!$G:$G,'Contas à Pagar'!$H:$H,">="&45717,'Contas à Pagar'!$H:$H,"<="&45747,'Contas à Pagar'!B:B,"Conta da clínica",'Contas à Pagar'!E:E,"Quitado",'Contas à Pagar'!B:B,$B$3) -> 0 | G8: =-SUMIFS('Contas à Pagar'!$G:$G,'Contas à Pagar'!$H:$H,">="&45748,'Contas à Pagar'!$H:$H,"<="&45777,'Contas à Pagar'!B:B,"Conta da clínica",'Contas à Pagar'!E:E,"Quitado",'Contas à Pagar'!B:B,$B$3) -> 0 | H8: =-SUMIFS('Contas à Pagar'!$G:$G,'Contas à Pagar'!$H:$H,">="&45778,'Contas à Pagar'!$H:$H,"<="&45808,'Contas à Pagar'!B:B,"Conta da clínica",'Contas à Pagar'!E:E,"Quitado",'Contas à Pagar'!B:B,$B$3) -> 0 | I8: =-SUMIFS('Contas à Pagar'!$G:$G,'Contas à Pagar'!$H:$H,">="&45809,'Contas à Pagar'!$H:$H,"<="&45838,'Contas à Pagar'!B:B,"Conta da clínica",'Contas à Pagar'!E:E,"Quitado",'Contas à Pagar'!B:B,$B$3) -> 0 | J8: =-SUMIFS('Contas à Pagar'!$G:$G,'Contas à Pagar'!$H:$H,">="&45839,'Contas à Pagar'!$H:$H,"<="&45869,'Contas à Pagar'!B:B,"Conta da clínica",'Contas à Pagar'!E:E,"Quitado",'Contas à Pagar'!B:B,$B$3) -> 0 | K8: =-SUMIFS('Contas à Pagar'!$G:$G,'Contas à Pagar'!$H:$H,">="&45870,'Contas à Pagar'!$H:$H,"<="&45900,'Contas à Pagar'!B:B,"Conta da clínica",'Contas à Pagar'!E:E,"Quitado",'Contas à Pagar'!B:B,$B$3) -> 0 | L8: =-SUMIFS('Contas à Pagar'!$G:$G,'Contas à Pagar'!$H:$H,">="&45901,'Contas à Pagar'!$H:$H,"<="&45930,'Contas à Pagar'!B:B,"Conta da clínica",'Contas à Pagar'!E:E,"Quitado",'Contas à Pagar'!B:B,$B$3) -> 0 | M8: =-SUMIFS('Contas à Pagar'!$G:$G,'Contas à Pagar'!$H:$H,">="&45931,'Contas à Pagar'!$H:$H,"<="&45961,'Contas à Pagar'!B:B,"Conta da clínica",'Contas à Pagar'!E:E,"Quitado",'Contas à Pagar'!B:B,$B$3) -> 0 | N8: =-SUMIFS('Contas à Pagar'!$G:$G,'Contas à Pagar'!$H:$H,">="&45962,'Contas à Pagar'!$H:$H,"<="&45991,'Contas à Pagar'!B:B,"Conta da clínica",'Contas à Pagar'!E:E,"Quitado",'Contas à Pagar'!B:B,$B$3) -> 0 | O8: =-SUMIFS('Contas à Pagar'!$G:$G,'Contas à Pagar'!$H:$H,">="&45992,'Contas à Pagar'!$H:$H,"<="&46022,'Contas à Pagar'!B:B,"Conta da clínica",'Contas à Pagar'!E:E,"Quitado",'Contas à Pagar'!B:B,$B$3) -> 0
B9: Comissões | C9: =SUM(D9:O9) -> 0 | D9: =-SUMIFS('Atendimentos à Receber'!$S:$S,'Atendimentos à Receber'!$V:$V,">="&45658,'Atendimentos à Receber'!$V:$V,"<="&45688,'Atendimentos à Receber'!$E:$E,$B$3) -> 0 | E9: =-SUMIFS('Atendimentos à Receber'!$S:$S,'Atendimentos à Receber'!$V:$V,">="&45689,'Atendimentos à Receber'!$V:$V,"<="&45716,'Atendimentos à Receber'!$E:$E,$B$3) -> 0 | F9: =-SUMIFS('Atendimentos à Receber'!$S:$S,'Atendimentos à Receber'!$V:$V,">="&45717,'Atendimentos à Receber'!$V:$V,"<="&45748,'Atendimentos à Receber'!$E:$E,$B$3) -> 0 | G9: =-SUMIFS('Atendimentos à Receber'!$S:$S,'Atendimentos à Receber'!$V:$V,">="&45748,'Atendimentos à Receber'!$V:$V,"<="&45777,'Atendimentos à Receber'!$E:$E,$B$3) -> 0 | H9: =-SUMIFS('Atendimentos à Receber'!$S:$S,'Atendimentos à Receber'!$V:$V,">="&45778,'Atendimentos à Receber'!$V:$V,"<="&45808,'Atendimentos à Receber'!$E:$E,$B$3) -> 0 | I9: =-SUMIFS('Atendimentos à Receber'!$S:$S,'Atendimentos à Receber'!$V:$V,">="&45809,'Atendimentos à Receber'!$V:$V,"<="&45838,'Atendimentos à Receber'!$E:$E,$B$3) -> 0 | J9: =-SUMIFS('Atendimentos à Receber'!$S:$S,'Atendimentos à Receber'!$V:$V,">="&45839,'Atendimentos à Receber'!$V:$V,"<="&45869,'Atendimentos à Receber'!$E:$E,$B$3) -> 0 | K9: =-SUMIFS('Atendimentos à Receber'!$S:$S,'Atendimentos à Receber'!$V:$V,">="&45870,'Atendimentos à Receber'!$V:$V,"<="&45900,'Atendimentos à Receber'!$E:$E,$B$3) -> 0 | L9: =-SUMIFS('Atendimentos à Receber'!$S:$S,'Atendimentos à Receber'!$V:$V,">="&45901,'Atendimentos à Receber'!$V:$V,"<="&45930,'Atendimentos à Receber'!$E:$E,$B$3) -> 0 | M9: =-SUMIFS('Atendimentos à Receber'!$S:$S,'Atendimentos à Receber'!$V:$V,">="&45931,'Atendimentos à Receber'!$V:$V,"<="&45961,'Atendimentos à Receber'!$E:$E,$B$3) -> 0 | N9: =-SUMIFS('Atendimentos à Receber'!$S:$S,'Atendimentos à Receber'!$V:$V,">="&45962,'Atendimentos à Receber'!$V:$V,"<="&45991,'Atendimentos à Receber'!$E:$E,$B$3) -> 0 | O9: =-SUMIFS('Atendimentos à Receber'!$S:$S,'Atendimentos à Receber'!$V:$V,">="&45992,'Atendimentos à Receber'!$V:$V,"<="&46022,'Atendimentos à Receber'!$E:$E,$B$3) -> 0
B10: Lucro Líquido | C10: =SUM(D10:O10) -> 0 | D10: =D4+D7 -> 0 | E10: =E4+E7 -> 0 | F10: =F4+F7 -> 0 | G10: =G4+G7 -> 0 | H10: =H4+H7 -> 0 | I10: =I4+I7 -> 0 | J10: =J4+J7 -> 0 | K10: =K4+K7 -> 0 | ... O10: =O4+O7 -> 0
B16: Resultados em Aberto do Profissional
C18: Acumulado no Ano | D18: 45292 | E18: 45323 | F18: 45352 | G18: 45383 | H18: 45413 | I18: 45444 | J18: 45474 | K18: 45505 | L18: 45536 | M18: 45566 | N18: 45597 | O18: 45627
B19: Faturamento em Aberto | C19: =SUM(D19:O19) -> 0 | D19: =SUM(D20:D21) -> 0 | E19: =SUM(E20:E21) -> 0 | F19: =SUM(F20:F21) -> 0 | G19: =SUM(G20:G21) -> 0 | H19: =SUM(H20:H21) -> 0 | I19: =SUM(I20:I21) -> 0 | J19: =SUM(J20:J21) -> 0 | K19: =SUM(K20:K21) -> 0 | ... O19: =SUM(O20:O21) -> 0
B20: Recebimento Pacientes | C20: =SUM(D20:O20) -> 0 | D20: =SUMIFS('Atendimentos à Receber'!$S:$S,'Atendimentos à Receber'!$V:$V,">="&45658,'Atendimentos à Receber'!$V:$V,"<="&45688,'Atendimentos à Receber'!$E:$E,$B$3)-SUMIFS('Atendimentos à Receber'!$R:$R,'Atendimentos à Receber'!$V:$V,">="&45658,'Atendimentos à Receber'!$V:$V,"<="&45688,'Atendimentos à Receber'!$E:$E,$B$3) -> 0 | E20: =SUMIFS('Atendimentos à Receber'!$S:$S,'Atendimentos à Receber'!$V:$V,">="&45689,'Atendimentos à Receber'!$V:$V,"<="&45716,'Atendimentos à Receber'!$E:$E,$B$3)-SUMIFS('Atendimentos à Receber'!$R:$R,'Atendimentos à Receber'!$V:$V,">="&45689,'Atendimentos à Receber'!$V:$V,"<="&45716,'Atendimentos à Receber'!$E:$E,$B$3) -> 0 | F20: =SUMIFS('Atendimentos à Receber'!$S:$S,'Atendimentos à Receber'!$V:$V,">="&45717,'Atendimentos à Receber'!$V:$V,"<="&45748,'Atendimentos à Receber'!$E:$E,$B$3)-SUMIFS('Atendimentos à Receber'!$R:$R,'Atendimentos à Receber'!$V:$V,">="&45717,'Atendimentos à Receber'!$V:$V,"<="&45748,'Atendimentos à Receber'!$E:$E,$B$3) -> 0 | G20: =SUMIFS('Atendimentos à Receber'!$S:$S,'Atendimentos à Receber'!$V:$V,">="&45748,'Atendimentos à Receber'!$V:$V,"<="&45777,'Atendimentos à Receber'!$E:$E,$B$3)-SUMIFS('Atendimentos à Receber'!$R:$R,'Atendimentos à Receber'!$V:$V,">="&45748,'Atendimentos à Receber'!$V:$V,"<="&45777,'Atendimentos à Receber'!$E:$E,$B$3) -> 0 | H20: =SUMIFS('Atendimentos à Receber'!$S:$S,'Atendimentos à Receber'!$V:$V,">="&45778,'Atendimentos à Receber'!$V:$V,"<="&45808,'Atendimentos à Receber'!$E:$E,$B$3)-SUMIFS('Atendimentos à Receber'!$R:$R,'Atendimentos à Receber'!$V:$V,">="&45778,'Atendimentos à Receber'!$V:$V,"<="&45808,'Atendimentos à Receber'!$E:$E,$B$3) -> 0 | I20: =SUMIFS('Atendimentos à Receber'!$S:$S,'Atendimentos à Receber'!$V:$V,">="&45809,'Atendimentos à Receber'!$V:$V,"<="&45838,'Atendimentos à Receber'!$E:$E,$B$3)-SUMIFS('Atendimentos à Receber'!$R:$R,'Atendimentos à Receber'!$V:$V,">="&45809,'Atendimentos à Receber'!$V:$V,"<="&45838,'Atendimentos à Receber'!$E:$E,$B$3) -> 0 | J20: =SUMIFS('Atendimentos à Receber'!$S:$S,'Atendimentos à Receber'!$V:$V,">="&45839,'Atendimentos à Receber'!$V:$V,"<="&45869,'Atendimentos à Receber'!$E:$E,$B$3)-SUMIFS('Atendimentos à Receber'!$R:$R,'Atendimentos à Receber'!$V:$V,">="&45839,'Atendimentos à Receber'!$V:$V,"<="&45869,'Atendimentos à Receber'!$E:$E,$B$3) -> 0 | K20: =SUMIFS('Atendimentos à Receber'!$S:$S,'Atendimentos à Receber'!$V:$V,">="&45870,'Atendimentos à Receber'!$V:$V,"<="&45900,'Atendimentos à Receber'!$E:$E,$B$3)-SUMIFS('Atendimentos à Receber'!$R:$R,'Atendimentos à Receber'!$V:$V,">="&45870,'Atendimentos à Receber'!$V:$V,"<="&45900,'Atendimentos à Receber'!$E:$E,$B$3) -> 0 | L20: =SUMIFS('Atendimentos à Receber'!$S:$S,'Atendimentos à Receber'!$V:$V,">="&45901,'Atendimentos à Receber'!$V:$V,"<="&45930,'Atendimentos à Receber'!$E:$E,$B$3)-SUMIFS('Atendimentos à Receber'!$R:$R,'Atendimentos à Receber'!$V:$V,">="&45901,'Atendimentos à Receber'!$V:$V,"<="&45930,'Atendimentos à Receber'!$E:$E,$B$3) -> 0 | M20: =SUMIFS('Atendimentos à Receber'!$S:$S,'Atendimentos à Receber'!$V:$V,">="&45931,'Atendimentos à Receber'!$V:$V,"<="&45961,'Atendimentos à Receber'!$E:$E,$B$3)-SUMIFS('Atendimentos à Receber'!$R:$R,'Atendimentos à Receber'!$V:$V,">="&45931,'Atendimentos à Receber'!$V:$V,"<="&45961,'Atendimentos à Receber'!$E:$E,$B$3) -> 0 | N20: =SUMIFS('Atendimentos à Receber'!$S:$S,'Atendimentos à Receber'!$V:$V,">="&45962,'Atendimentos à Receber'!$V:$V,"<="&45991,'Atendimentos à Receber'!$E:$E,$B$3)-SUMIFS('Atendimentos à Receber'!$R:$R,'Atendimentos à Receber'!$V:$V,">="&45962,'Atendimentos à Receber'!$V:$V,"<="&45991,'Atendimentos à Receber'!$E:$E,$B$3) -> 0 | O20: =SUMIFS('Atendimentos à Receber'!$S:$S,'Atendimentos à Receber'!$V:$V,">="&45992,'Atendimentos à Receber'!$V:$V,"<="&46022,'Atendimentos à Receber'!$E:$E,$B$3)-SUMIFS('Atendimentos à Receber'!$R:$R,'Atendimentos à Receber'!$V:$V,">="&45992,'Atendimentos à Receber'!$V:$V,"<="&46022,'Atendimentos à Receber'!$E:$E,$B$3) -> 0
B21: Outros Recebimentos | C21: =SUM(D21:O21) -> 0 | D21: =SUMIFS('Outras Contas à Receber'!$H:$H,'Outras Contas à Receber'!$I:$I,">="&45658,'Outras Contas à Receber'!$I:$I,"<="&45688,'Outras Contas à Receber'!$B:$B,$B$3)-SUMIFS('Outras Contas à Receber'!$G:$G,'Outras Contas à Receber'!$I:$I,">="&45658,'Outras Contas à Receber'!$I:$I,"<="&45688,'Outras Contas à Receber'!$B:$B,$B$3) -> 0 | E21: =SUMIFS('Outras Contas à Receber'!$H:$H,'Outras Contas à Receber'!$I:$I,">="&45689,'Outras Contas à Receber'!$I:$I,"<="&45716,'Outras Contas à Receber'!$B:$B,$B$3)-SUMIFS('Outras Contas à Receber'!$G:$G,'Outras Contas à Receber'!$I:$I,">="&45689,'Outras Contas à Receber'!$I:$I,"<="&45716,'Outras Contas à Receber'!$B:$B,$B$3) -> 0 | F21: =SUMIFS('Outras Contas à Receber'!$H:$H,'Outras Contas à Receber'!$I:$I,">="&45717,'Outras Contas à Receber'!$I:$I,"<="&45747,'Outras Contas à Receber'!$B:$B,$B$3)-SUMIFS('Outras Contas à Receber'!$G:$G,'Outras Contas à Receber'!$I:$I,">="&45717,'Outras Contas à Receber'!$I:$I,"<="&45747,'Outras Contas à Receber'!$B:$B,$B$3) -> 0 | G21: =SUMIFS('Outras Contas à Receber'!$H:$H,'Outras Contas à Receber'!$I:$I,">="&45748,'Outras Contas à Receber'!$I:$I,"<="&45777,'Outras Contas à Receber'!$B:$B,$B$3)-SUMIFS('Outras Contas à Receber'!$G:$G,'Outras Contas à Receber'!$I:$I,">="&45748,'Outras Contas à Receber'!$I:$I,"<="&45777,'Outras Contas à Receber'!$B:$B,$B$3) -> 0 | H21: =SUMIFS('Outras Contas à Receber'!$H:$H,'Outras Contas à Receber'!$I:$I,">="&45778,'Outras Contas à Receber'!$I:$I,"<="&45808,'Outras Contas à Receber'!$B:$B,$B$3)-SUMIFS('Outras Contas à Receber'!$G:$G,'Outras Contas à Receber'!$I:$I,">="&45778,'Outras Contas à Receber'!$I:$I,"<="&45808,'Outras Contas à Receber'!$B:$B,$B$3) -> 0 | I21: =SUMIFS('Outras Contas à Receber'!$H:$H,'Outras Contas à Receber'!$I:$I,">="&45809,'Outras Contas à Receber'!$I:$I,"<="&45838,'Outras Contas à Receber'!$B:$B,$B$3)-SUMIFS('Outras Contas à Receber'!$G:$G,'Outras Contas à Receber'!$I:$I,">="&45809,'Outras Contas à Receber'!$I:$I,"<="&45838,'Outras Contas à Receber'!$B:$B,$B$3) -> 0 | J21: =SUMIFS('Outras Contas à Receber'!$H:$H,'Outras Contas à Receber'!$I:$I,">="&45839,'Outras Contas à Receber'!$I:$I,"<="&45869,'Outras Contas à Receber'!$B:$B,$B$3)-SUMIFS('Outras Contas à Receber'!$G:$G,'Outras Contas à Receber'!$I:$I,">="&45839,'Outras Contas à Receber'!$I:$I,"<="&45869,'Outras Contas à Receber'!$B:$B,$B$3) -> 0 | K21: =SUMIFS('Outras Contas à Receber'!$H:$H,'Outras Contas à Receber'!$I:$I,">="&45870,'Outras Contas à Receber'!$I:$I,"<="&45900,'Outras Contas à Receber'!$B:$B,$B$3)-SUMIFS('Outras Contas à Receber'!$G:$G,'Outras Contas à Receber'!$I:$I,">="&45870,'Outras Contas à Receber'!$I:$I,"<="&45900,'Outras Contas à Receber'!$B:$B,$B$3) -> 0 | L21: =SUMIFS('Outras Contas à Receber'!$H:$H,'Outras Contas à Receber'!$I:$I,">="&45901,'Outras Contas à Receber'!$I:$I,"<="&45930,'Outras Contas à Receber'!$B:$B,$B$3)-SUMIFS('Outras Contas à Receber'!$G:$G,'Outras Contas à Receber'!$I:$I,">="&45901,'Outras Contas à Receber'!$I:$I,"<="&45930,'Outras Contas à Receber'!$B:$B,$B$3) -> 0 | M21: =SUMIFS('Outras Contas à Receber'!$H:$H,'Outras Contas à Receber'!$I:$I,">="&45931,'Outras Contas à Receber'!$I:$I,"<="&45961,'Outras Contas à Receber'!$B:$B,$B$3)-SUMIFS('Outras Contas à Receber'!$G:$G,'Outras Contas à Receber'!$I:$I,">="&45931,'Outras Contas à Receber'!$I:$I,"<="&45961,'Outras Contas à Receber'!$B:$B,$B$3) -> 0 | N21: =SUMIFS('Outras Contas à Receber'!$H:$H,'Outras Contas à Receber'!$I:$I,">="&45962,'Outras Contas à Receber'!$I:$I,"<="&45991,'Outras Contas à Receber'!$B:$B,$B$3)-SUMIFS('Outras Contas à Receber'!$G:$G,'Outras Contas à Receber'!$I:$I,">="&45962,'Outras Contas à Receber'!$I:$I,"<="&45991,'Outras Contas à Receber'!$B:$B,$B$3) -> 0 | O21: =SUMIFS('Outras Contas à Receber'!$H:$H,'Outras Contas à Receber'!$I:$I,">="&45992,'Outras Contas à Receber'!$I:$I,"<="&46022,'Outras Contas à Receber'!$B:$B,$B$3)-SUMIFS('Outras Contas à Receber'!$G:$G,'Outras Contas à Receber'!$I:$I,">="&45992,'Outras Contas à Receber'!$I:$I,"<="&46022,'Outras Contas à Receber'!$B:$B,$B$3) -> 0
B22: Custos em Aberto | C22: =SUM(D22:O22) -> 0 | D22: =SUM(D23:D24) -> 0 | E22: =SUM(E23:E24) -> 0 | F22: =SUM(F23:F24) -> 0 | G22: =SUM(G23:G24) -> 0 | H22: =SUM(H23:H24) -> 0 | I22: =SUM(I23:I24) -> 0 | J22: =SUM(J23:J24) -> 0 | K22: =SUM(K23:K24) -> 0 | ... O22: =SUM(O23:O24) -> 0
B23: Custos | C23: =SUM(D23:O23) -> 0 | D23: =-SUMIFS('Contas à Pagar'!$G:$G,'Contas à Pagar'!$H:$H,">="&45658,'Contas à Pagar'!$H:$H,"<="&45688,'Contas à Pagar'!B:B,"Conta da clínica",'Contas à Pagar'!E:E,"Em Aberto",'Contas à Pagar'!B:B,$B$3) -> 0 | E23: =-SUMIFS('Contas à Pagar'!$G:$G,'Contas à Pagar'!$H:$H,">="&45689,'Contas à Pagar'!$H:$H,"<="&45716,'Contas à Pagar'!B:B,"Conta da clínica",'Contas à Pagar'!E:E,"Em Aberto",'Contas à Pagar'!B:B,$B$3) -> 0 | F23: =-SUMIFS('Contas à Pagar'!$G:$G,'Contas à Pagar'!$H:$H,">="&45717,'Contas à Pagar'!$H:$H,"<="&45747,'Contas à Pagar'!B:B,"Conta da clínica",'Contas à Pagar'!E:E,"Em Aberto",'Contas à Pagar'!B:B,$B$3) -> 0 | G23: =-SUMIFS('Contas à Pagar'!$G:$G,'Contas à Pagar'!$H:$H,">="&45748,'Contas à Pagar'!$H:$H,"<="&45777,'Contas à Pagar'!B:B,"Conta da clínica",'Contas à Pagar'!E:E,"Em Aberto",'Contas à Pagar'!B:B,$B$3) -> 0 | H23: =-SUMIFS('Contas à Pagar'!$G:$G,'Contas à Pagar'!$H:$H,">="&45778,'Contas à Pagar'!$H:$H,"<="&45808,'Contas à Pagar'!B:B,"Conta da clínica",'Contas à Pagar'!E:E,"Em Aberto",'Contas à Pagar'!B:B,$B$3) -> 0 | I23: =-SUMIFS('Contas à Pagar'!$G:$G,'Contas à Pagar'!$H:$H,">="&45809,'Contas à Pagar'!$H:$H,"<="&45838,'Contas à Pagar'!B:B,"Conta da clínica",'Contas à Pagar'!E:E,"Em Aberto",'Contas à Pagar'!B:B,$B$3) -> 0 | J23: =-SUMIFS('Contas à Pagar'!$G:$G,'Contas à Pagar'!$H:$H,">="&45839,'Contas à Pagar'!$H:$H,"<="&45869,'Contas à Pagar'!B:B,"Conta da clínica",'Contas à Pagar'!E:E,"Em Aberto",'Contas à Pagar'!B:B,$B$3) -> 0 | K23: =-SUMIFS('Contas à Pagar'!$G:$G,'Contas à Pagar'!$H:$H,">="&45870,'Contas à Pagar'!$H:$H,"<="&45900,'Contas à Pagar'!B:B,"Conta da clínica",'Contas à Pagar'!E:E,"Em Aberto",'Contas à Pagar'!B:B,$B$3) -> 0 | L23: =-SUMIFS('Contas à Pagar'!$G:$G,'Contas à Pagar'!$H:$H,">="&45901,'Contas à Pagar'!$H:$H,"<="&45930,'Contas à Pagar'!B:B,"Conta da clínica",'Contas à Pagar'!E:E,"Em Aberto",'Contas à Pagar'!B:B,$B$3) -> 0 | M23: =-SUMIFS('Contas à Pagar'!$G:$G,'Contas à Pagar'!$H:$H,">="&45931,'Contas à Pagar'!$H:$H,"<="&45961,'Contas à Pagar'!B:B,"Conta da clínica",'Contas à Pagar'!E:E,"Em Aberto",'Contas à Pagar'!B:B,$B$3) -> 0 | N23: =-SUMIFS('Contas à Pagar'!$G:$G,'Contas à Pagar'!$H:$H,">="&45962,'Contas à Pagar'!$H:$H,"<="&45991,'Contas à Pagar'!B:B,"Conta da clínica",'Contas à Pagar'!E:E,"Em Aberto",'Contas à Pagar'!B:B,$B$3) -> 0 | O23: =-SUMIFS('Contas à Pagar'!$G:$G,'Contas à Pagar'!$H:$H,">="&45992,'Contas à Pagar'!$H:$H,"<="&46022,'Contas à Pagar'!B:B,"Conta da clínica",'Contas à Pagar'!E:E,"Em Aberto",'Contas à Pagar'!B:B,$B$3) -> 0
B24: Comissões | C24: =SUM(D24:O24) -> 0 | D24: =-SUMIFS('Atendimentos à Receber'!$U:$U,'Atendimentos à Receber'!$V:$V,">="&45658,'Atendimentos à Receber'!$V:$V,"<="&45688,'Atendimentos à Receber'!$E:$E,$B$3) -> 0 | E24: =-SUMIFS('Atendimentos à Receber'!$U:$U,'Atendimentos à Receber'!$V:$V,">="&45689,'Atendimentos à Receber'!$V:$V,"<="&45716,'Atendimentos à Receber'!$E:$E,$B$3) -> 0 | F24: =-SUMIFS('Atendimentos à Receber'!$U:$U,'Atendimentos à Receber'!$V:$V,">="&45717,'Atendimentos à Receber'!$V:$V,"<="&45748,'Atendimentos à Receber'!$E:$E,$B$3) -> 0 | G24: =-SUMIFS('Atendimentos à Receber'!$U:$U,'Atendimentos à Receber'!$V:$V,">="&45748,'Atendimentos à Receber'!$V:$V,"<="&45777,'Atendimentos à Receber'!$E:$E,$B$3) -> 0 | H24: =-SUMIFS('Atendimentos à Receber'!$U:$U,'Atendimentos à Receber'!$V:$V,">="&45778,'Atendimentos à Receber'!$V:$V,"<="&45808,'Atendimentos à Receber'!$E:$E,$B$3) -> 0 | I24: =-SUMIFS('Atendimentos à Receber'!$U:$U,'Atendimentos à Receber'!$V:$V,">="&45809,'Atendimentos à Receber'!$V:$V,"<="&45838,'Atendimentos à Receber'!$E:$E,$B$3) -> 0 | J24: =-SUMIFS('Atendimentos à Receber'!$U:$U,'Atendimentos à Receber'!$V:$V,">="&45839,'Atendimentos à Receber'!$V:$V,"<="&45869,'Atendimentos à Receber'!$E:$E,$B$3) -> 0 | K24: =-SUMIFS('Atendimentos à Receber'!$U:$U,'Atendimentos à Receber'!$V:$V,">="&45870,'Atendimentos à Receber'!$V:$V,"<="&45900,'Atendimentos à Receber'!$E:$E,$B$3) -> 0 | L24: =-SUMIFS('Atendimentos à Receber'!$U:$U,'Atendimentos à Receber'!$V:$V,">="&45901,'Atendimentos à Receber'!$V:$V,"<="&45930,'Atendimentos à Receber'!$E:$E,$B$3) -> 0 | M24: =-SUMIFS('Atendimentos à Receber'!$U:$U,'Atendimentos à Receber'!$V:$V,">="&45931,'Atendimentos à Receber'!$V:$V,"<="&45961,'Atendimentos à Receber'!$E:$E,$B$3) -> 0 | N24: =-SUMIFS('Atendimentos à Receber'!$U:$U,'Atendimentos à Receber'!$V:$V,">="&45962,'Atendimentos à Receber'!$V:$V,"<="&45991,'Atendimentos à Receber'!$E:$E,$B$3) -> 0 | O24: =-SUMIFS('Atendimentos à Receber'!$U:$U,'Atendimentos à Receber'!$V:$V,">="&45992,'Atendimentos à Receber'!$V:$V,"<="&46022,'Atendimentos à Receber'!$E:$E,$B$3) -> 0
B25: Lucro em Aberto | C25: =SUM(D25:O25) -> 0 | D25: =D19+D22 -> 0 | E25: =E19+E22 -> 0 | F25: =F19+F22 -> 0 | G25: =G19+G22 -> 0 | H25: =H19+H22 -> 0 | I25: =I19+I22 -> 0 | J25: =J19+J22 -> 0 | K25: =K19+K22 -> 0 | ... O25: =O19+O22 -> 0

Sheet Atendimentos à Receber
A1: Paciente | B1: CPF | C1: Telefone | D1: Data | E1: Profissional | F1: Criado Por | G1: Data de Nascimento | H1: Sala | I1: Serviço | J1: Convênio | K1: Recorrência | L1: Status | M1: Etiqueta | N1: Pagamento | O1: Data de Pagamento | P1: Observação de Pagamento | Q1: Método de Pagamento | R1: Valor Pago | S1: Valor Total | T1: Comissão Paga | U1: Total de Comissão | V1: Data Agendamento Valor
V2: =IFERROR(DATEVALUE(D2),"")
V3: =IFERROR(DATEVALUE(D3),"")
V4: =IFERROR(DATEVALUE(D4),"")
V5: =IFERROR(DATEVALUE(D5),"")
V6: =IFERROR(DATEVALUE(D6),"")
V7: =IFERROR(DATEVALUE(D7),"")
V8: =IFERROR(DATEVALUE(D8),"")
V9: =IFERROR(DATEVALUE(D9),"")
V10: =IFERROR(DATEVALUE(D10),"")
V11: =IFERROR(DATEVALUE(D11),"")
V12: =IFERROR(DATEVALUE(D12),"")
V13: =IFERROR(DATEVALUE(D13),"")
... V3001: =IFERROR(DATEVALUE(D3001),"")

Sheet Outras Contas à Receber
A1: Nome | B1: Profissional | C1: Paciente | D1: Data | E1: Parcela | F1: Status | G1: Valor Pago | H1: Valor | I1: Data Recebimento
I2: =IFERROR(DATEVALUE(D2),"")
I3: =IFERROR(DATEVALUE(D3),"")
I4: =IFERROR(DATEVALUE(D4),"")
I5: =IFERROR(DATEVALUE(D5),"")
I6: =IFERROR(DATEVALUE(D6),"")
I7: =IFERROR(DATEVALUE(D7),"")
I8: =IFERROR(DATEVALUE(D8),"")
I9: =IFERROR(DATEVALUE(D9),"")
I10: =IFERROR(DATEVALUE(D10),"")
I11: =IFERROR(DATEVALUE(D11),"")
I12: =IFERROR(DATEVALUE(D12),"")
I13: =IFERROR(DATEVALUE(D13),"")
... I3000: =IFERROR(DATEVALUE(D3000),"")

Sheet Contas à Pagar
A1: Nome | B1: Profissional | C1: Data | D1: Parcela | E1: Status | F1: Valor Pago | G1: Valor | H1: Data Pagamento
H2: =IFERROR(DATEVALUE(C2),"")
H3: =IFERROR(DATEVALUE(C3),"")
H4: =IFERROR(DATEVALUE(C4),"")
H5: =IFERROR(DATEVALUE(C5),"")
H6: =IFERROR(DATEVALUE(C6),"")
H7: =IFERROR(DATEVALUE(C7),"")
H8: =IFERROR(DATEVALUE(C8),"")
H9: =IFERROR(DATEVALUE(C9),"")
H10: =IFERROR(DATEVALUE(C10),"")
H11: =IFERROR(DATEVALUE(C11),"")
H12: =IFERROR(DATEVALUE(C12),"")
H13: =IFERROR(DATEVALUE(C13),"")
... H3000: =IFERROR(DATEVALUE(C3000),"")
